autograder_sandbox/__init__.py
autograder_sandbox/autograder_sandbox.py
autograder_sandbox/output_size_performance_test.py
autograder_sandbox/py.typed
autograder_sandbox/tests.py
autograder_sandbox/version.py
autograder_sandbox/docker-image-setup/Dockerfile
autograder_sandbox/docker-image-setup/cmd_runner.py
autograder_sandbox/reaper/Dockerfile
autograder_sandbox/reaper/reap.py
autograder_sandbox-6.0.0.dist-info/licenses/LICENSE.txt
autograder_sandbox-6.0.0.dist-info/METADATA
autograder_sandbox-6.0.0.dist-info/WHEEL
autograder_sandbox-6.0.0.dist-info/top_level.txt
autograder_sandbox-6.0.0.dist-info/RECORD
