Metadata-Version: 2.4
Name: autograder-sandbox
Version: 6.0.0
Summary: Python library for running untrusted code in Docker containers.
Author-email: James Perretta <jameslp@umich.edu>
Project-URL: Homepage, https://github.com/eecs-autograder/autograder-sandbox
Project-URL: Issues, https://github.com/eecs-autograder/autograder-sandbox/issues
Keywords: autograder,autograder.io
Classifier: Programming Language :: Python :: 3
Classifier: License :: OSI Approved :: GNU Lesser General Public License v3 (LGPLv3)
Requires-Python: >=3.10
License-File: LICENSE.txt
Dynamic: license-file
